UltraDict.cp314-win32.pyd
UltraDict/Exceptions.py
UltraDict/UltraDict.py
UltraDict/__init__.py
UltraDict/setup.py
ultradict_wheels-0.0.6.dist-info/licenses/LICENSE
ultradict_wheels-0.0.6.dist-info/METADATA
ultradict_wheels-0.0.6.dist-info/WHEEL
ultradict_wheels-0.0.6.dist-info/top_level.txt
ultradict_wheels-0.0.6.dist-info/RECORD
