Metadata-Version: 2.4
Name: UltraDict-wheels
Version: 0.0.6
Summary: Sychronized, streaming dictionary that uses shared memory as a backend
Home-page: https://github.com/ronny-rentner/UltraDict
Author: Ronny Rentner
Author-email: ultradict.code@ronny-rentner.de
Requires-Python: >=3.9
License-File: LICENSE
Dynamic: author
Dynamic: author-email
Dynamic: description
Dynamic: description-content-type
Dynamic: home-page
Dynamic: license-file
Dynamic: requires-python
Dynamic: summary
